pygranso/__init__.py
pygranso/pygranso.py
pygranso/pygransoOptions.py
pygranso/pygransoOptionsAdvanced.py
pygranso/pygransoStruct.py
pygranso/private/__init__.py
pygranso/private/bfgsDamping.py
pygranso/private/bfgsHessianInverse.py
pygranso/private/bfgsHessianInverseLimitedMem.py
pygranso/private/bfgssqp.py
pygranso/private/centerString.py
pygranso/private/copyrightNotice.py
pygranso/private/double2FixedWidthStr.py
pygranso/private/formatOrange.py
pygranso/private/getCiGradVec.py
pygranso/private/getCiVec.py
pygranso/private/getNvar.py
pygranso/private/getObjGrad.py
pygranso/private/isARealNumber.py
pygranso/private/isAnInteger.py
pygranso/private/isBlankStr.py
pygranso/private/isColumn.py
pygranso/private/isFiniteValued.py
pygranso/private/isMbyN.py
pygranso/private/isPositiveDefinite.py
pygranso/private/isRealValued.py
pygranso/private/isRestartData.py
pygranso/private/isRow.py
pygranso/private/isString.py
pygranso/private/isStruct.py
pygranso/private/isTorchDevice.py
pygranso/private/linesearchWeakWolfe.py
pygranso/private/makePenaltyFunction.py
pygranso/private/makeStructWithFields.py
pygranso/private/nDigitsInWholePart.py
pygranso/private/neighborhoodCache.py
pygranso/private/optionValidator.py
pygranso/private/printMessageBox.py
pygranso/private/printOrange.py
pygranso/private/processVarSpec.py
pygranso/private/pygransoConstants.py
pygranso/private/pygransoPrinter.py
pygranso/private/pygransoPrinterColumns.py
pygranso/private/qpSteeringStrategy.py
pygranso/private/qpTerminationCondition.py
pygranso/private/regularizePosDefMatrix.py
pygranso/private/solveQP.py
pygranso/private/tablePrinter.py
pygranso/private/tensor2vec.py
pygranso/private/truncate.py
pygranso/private/vec2tensor.py
pygranso/private/wrapToLines.py
pygranso-1.2.0.dist-info/AUTHORS.md
pygranso-1.2.0.dist-info/LICENSE
pygranso-1.2.0.dist-info/METADATA
pygranso-1.2.0.dist-info/WHEEL
pygranso-1.2.0.dist-info/top_level.txt
pygranso-1.2.0.dist-info/RECORD
