Metadata-Version: 2.1
Name: pygranso
Version: 1.2.0
Summary: PyGRANSO: A PyTorch-enabled port of GRANSO with auto-differentiation
Home-page: https://github.com/sun-umn/PyGRANSO
Author: Tim Mitchell and Buyun Liang
Author-email: liang664@umn.edu, tim@timmitchell.com
Project-URL: Bug Tracker, https://github.com/sun-umn/PyGRANSO/issues
Keywords: deep learning,machine learning,optimization software,mathematical software
Requires-Python: >=3.9
License-File: LICENSE
License-File: AUTHORS.md
